<?xml version="1.0" encoding="UTF-8" ?>
<metadatadoc version="2.0">
	<object type="Entity" id="2F397D33-7423-3F10-00C9-6B201805AD9B" rep_oid="null" rep_ovid="null" is_checkedout="false" checkedout_by="" visible_in_main_view="true" entitytype="" allow_type_substitution="true" strategy="Single Table" minVolumes="0" expectedVolumes="0" maxVolumes="9999999" growthPercent="0" growthType="Year" normalForm="Third" adequatelyNormalized="NO" use_default_color="true" background_color="null" foreground_color="null">
		<name>Status_Cliente</name>
		<comment></comment>
		<notes></notes>
		<alter type="created">
			<user>RicardoMMO</user>
			<timestamp>2010-08-04 19:59:11</timestamp>
		</alter>
		<alter type="changed">
			<user>RicardoMMO</user>
			<timestamp>2010-08-07 14:12:30</timestamp>
		</alter>
		<generator>86CAD2AA-82E4-9DC5-040B-BFA5CB1DFE5A</generator>
		<properties>
			<parameter name="design.owner" value="modelagem_ProjetoF1" />
			<parameter name="object.existsinrepository" value="true" />
			<parameter name="property.comment.rdbms" value="" />
		</properties>
		<parent inherits="false" />
		<engineering>
			<relational_design id="AFE48C82-B64B-0FBC-0646-6F912E0B84A0" should="true" />
		</engineering>
		<des_obj_version version="1.0" />
		<fonts>
			<font_object>
				<parameter name="fo_type" value="Title" />
				<parameter name="font_color" value="-16776961" />
				<parameter name="font_name" value="Dialog" />
				<parameter name="font_size" value="10" />
				<parameter name="font_style" value="1" />
			</font_object>
			<font_object>
				<parameter name="fo_type" value="Attribute" />
				<parameter name="font_color" value="-16777216" />
				<parameter name="font_name" value="Dialog" />
				<parameter name="font_size" value="10" />
				<parameter name="font_style" value="0" />
			</font_object>
			<font_object>
				<parameter name="fo_type" value="Datatype" />
				<parameter name="font_color" value="-16744448" />
				<parameter name="font_name" value="Dialog" />
				<parameter name="font_size" value="10" />
				<parameter name="font_style" value="0" />
			</font_object>
			<font_object>
				<parameter name="fo_type" value="PK Element" />
				<parameter name="font_color" value="-16776961" />
				<parameter name="font_name" value="Dialog" />
				<parameter name="font_size" value="10" />
				<parameter name="font_style" value="0" />
			</font_object>
			<font_object>
				<parameter name="fo_type" value="FK Element" />
				<parameter name="font_color" value="-16777216" />
				<parameter name="font_name" value="Dialog" />
				<parameter name="font_size" value="10" />
				<parameter name="font_style" value="0" />
			</font_object>
			<font_object>
				<parameter name="fo_type" value="UK Element" />
				<parameter name="font_color" value="-16776961" />
				<parameter name="font_name" value="Dialog" />
				<parameter name="font_size" value="10" />
				<parameter name="font_style" value="0" />
			</font_object>
			<font_object>
				<parameter name="fo_type" value="Not Null" />
				<parameter name="font_color" value="-65536" />
				<parameter name="font_name" value="Dialog" />
				<parameter name="font_size" value="10" />
				<parameter name="font_style" value="0" />
			</font_object>
			<font_object>
				<parameter name="fo_type" value="Key" />
				<parameter name="font_color" value="-16777216" />
				<parameter name="font_name" value="Dialog" />
				<parameter name="font_size" value="10" />
				<parameter name="font_style" value="0" />
			</font_object>
		</fonts>
		<documents />
		<parties />
		<changerequests />
		<measurements />
		<contained>
			<object type="Attribute" id="D46215D0-B3A8-665F-19F7-D7D40DA0E511" rep_oid="null" rep_ovid="null" is_checkedout="false" checkedout_by="" visible_in_main_view="false" use_default_color="true" background_color="null" foreground_color="null" unique="false" allownull="false" usedomainconstraints="true" is_oid="false" structured_attribute_id="" fk="false">
				<name>ID_STATUS_CLIENTE</name>
				<comment></comment>
				<notes></notes>
				<alter type="created">
					<user>RicardoMMO</user>
					<timestamp>2010-08-04 19:59:11</timestamp>
				</alter>
				<alter type="changed">
					<user>RicardoMMO</user>
					<timestamp>2010-08-04 20:41:20</timestamp>
				</alter>
				<generator>84EBAA94-5222-AC25-81C9-D7F5F867C932</generator>
				<properties>
					<parameter name="design.owner" value="modelagem_ProjetoF1" />
					<parameter name="object.existsinrepository" value="true" />
					<parameter name="object.property.defaultvalue" value="" />
					<parameter name="object.property.usesdefault" value="false" />
					<parameter name="property.comment.rdbms" value="" />
				</properties>
				<engineering>
					<relational_design id="AFE48C82-B64B-0FBC-0646-6F912E0B84A0" should="true" />
				</engineering>
				<des_obj_version version="1.0" />
				<domain oid="F61221CF-179E-CAE9-91CA-6BB0B0E34EB0" file="defaultdomains" />
				<datatype dttype="packed" precision="3" scale="0" typename="NUMBER" />
				<reference value="false" />
				<logicaltype dttype="NUMERIC" oid="LOGDT019" />
				<use value="domain" />
				<sourcetype sort="" />
				<formula desc="" />
				<subtypeSubstitution value="true" />
				<restricted_substitution value="false" />
				<source value="" />
				<documents />
				<parties />
				<changerequests />
				<measurements />
			</object>
			<object type="Attribute" id="338F025F-CF83-AA45-A4F0-9A5BA02E5BDC" rep_oid="null" rep_ovid="null" is_checkedout="false" checkedout_by="" visible_in_main_view="false" use_default_color="true" background_color="null" foreground_color="null" unique="false" allownull="false" usedomainconstraints="true" is_oid="false" structured_attribute_id="" fk="false">
				<name>DESCRICAO</name>
				<comment></comment>
				<notes></notes>
				<alter type="created">
					<user>RicardoMMO</user>
					<timestamp>2010-08-04 19:59:11</timestamp>
				</alter>
				<alter type="changed">
					<user>RicardoMMO</user>
					<timestamp>2010-08-04 22:27:58</timestamp>
				</alter>
				<generator>4EFA4B53-09EB-35EB-ED25-D81E4DB30688</generator>
				<properties>
					<parameter name="design.owner" value="modelagem_ProjetoF1" />
					<parameter name="object.existsinrepository" value="true" />
					<parameter name="object.property.defaultvalue" value="" />
					<parameter name="object.property.usesdefault" value="false" />
					<parameter name="property.comment.rdbms" value="" />
				</properties>
				<engineering>
					<relational_design id="AFE48C82-B64B-0FBC-0646-6F912E0B84A0" should="true" />
				</engineering>
				<des_obj_version version="1.0" />
				<domain oid="9B0ADAC5-A9F8-1C8C-DBF4-76AF27B546FD" file="defaultdomains" />
				<datatype dttype="var" size="100" typename="VARCHAR2" />
				<reference value="false" />
				<logicaltype dttype="VARCHAR" oid="LOGDT024" />
				<use value="domain" />
				<sourcetype sort="" />
				<formula desc="" />
				<subtypeSubstitution value="true" />
				<restricted_substitution value="false" />
				<source value="" />
				<documents />
				<parties />
				<changerequests />
				<measurements />
			</object>
		</contained>
		<key>
			<object type="Candidate Key" id="5FF1D09B-966B-C978-EDA1-8BAA7B5E50ED" rep_oid="null" rep_ovid="null" is_checkedout="false" checkedout_by="" visible_in_main_view="false" use_default_color="true" background_color="null" foreground_color="null" pk="true" keystate="Primary Key" synonym="">
				<name>PK_STATUSCLIENTE</name>
				<comment></comment>
				<notes></notes>
				<alter type="created">
					<user>RicardoMMO</user>
					<timestamp>2010-08-04 19:59:11</timestamp>
				</alter>
				<alter type="changed">
					<user>RicardoMMO</user>
					<timestamp>2010-08-04 20:25:33</timestamp>
				</alter>
				<generator>04689829-E1E1-26F4-6075-6E7E1A3DF4D1</generator>
				<properties>
					<parameter name="design.owner" value="modelagem_ProjetoF1" />
					<parameter name="object.existsinrepository" value="true" />
					<parameter name="property.comment.rdbms" value="" />
				</properties>
				<engineering>
					<relational_design id="AFE48C82-B64B-0FBC-0646-6F912E0B84A0" should="true" />
				</engineering>
				<des_obj_version version="1.0" />
				<contains type="Attribute">D46215D0-B3A8-665F-19F7-D7D40DA0E511</contains>
				<documents />
				<parties />
				<changerequests />
				<measurements />
			</object>
		</key>
	</object>
</metadatadoc>